xync_schema/__init__.py
xync_schema/enums.py
xync_schema/models.py
xync_schema/types.py
xync_schema-0.6.91.dist-info/METADATA
xync_schema-0.6.91.dist-info/WHEEL
xync_schema-0.6.91.dist-info/top_level.txt
xync_schema-0.6.91.dist-info/RECORD
