Metadata-Version: 2.4
Name: xync-schema
Version: 0.6.91
Summary: XyncNet project database model schema
Author-email: Mike Artemiev <mixartemev@gmail.com>
License: EULA
Project-URL: Homepage, https://gitlab.com/xync/back/schema
Project-URL: Repository, https://gitlab.com/xync/back/schema
Requires-Python: >=3.11
Requires-Dist: xn-auth
Requires-Dist: python-dotenv
Provides-Extra: dev
Requires-Dist: build; extra == "dev"
Requires-Dist: pre-commit; extra == "dev"
Requires-Dist: pytest-asyncio; extra == "dev"
Requires-Dist: twine; extra == "dev"
